{
    "entry":
    [
        {
            "timestamp": "2020-08-02T23:18:05.039Z",
            "name": "Kristy Thomas",
            "whichCityDoYouLiveIn": "Houston",
            "email": "kristy's email",
            "itemYouAreWillingToGive": "canned fruit",
            "itemYouNeed": "bananas"
        },
        {
            "timestamp": "2020-08-02T23:18:56.965Z",
            "name": "Claudia Kishi",
            "whichCityDoYouLiveIn": "San Antonio",
            "email": "claudia's email",
            "itemYouAreWillingToGive": "bananas",
            "itemYouNeed": "bread"
        },
        {
            "timestamp": "2020-08-02T23:19:53.126Z",
            "name": "Mary Anne Spier",
            "whichCityDoYouLiveIn": "Austin",
            "email": "mary anne's email",
            "itemYouAreWillingToGive": "rice",
            "itemYouNeed": "toilet paper"
        },
        {
            "timestamp": "2020-08-02T23:21:56.577Z",
            "name": "Stacey McGill",
            "whichCityDoYouLiveIn": "El Paso",
            "email": "stacey's email",
            "itemYouAreWillingToGive": "Clorox Wipes",
            "itemYouNeed": "canned fruit"
        }
    ]
    
}